AUTHORS.rst
CONTRIBUTING.rst
HISTORY.rst
LICENSE
MANIFEST.in
README.rst
setup.cfg
setup.py
docs/Makefile
docs/authors.rst
docs/conf.py
docs/contributing.rst
docs/history.rst
docs/index.rst
docs/installation.rst
docs/make.bat
docs/readme.rst
docs/usage.rst
ftl_events/__init__.py
ftl_events/cli.py
ftl_events/condition_parser.py
ftl_events/condition_types.py
ftl_events/durability.py
ftl_events/ftl_events.py
ftl_events/rule_generator.py
ftl_events/rule_types.py
ftl_events/rules_parser.py
ftl_events.egg-info/PKG-INFO
ftl_events.egg-info/SOURCES.txt
ftl_events.egg-info/dependency_links.txt
ftl_events.egg-info/entry_points.txt
ftl_events.egg-info/not-zip-safe
ftl_events.egg-info/requires.txt
ftl_events.egg-info/top_level.txt
tests/__init__.py
tests/animal.py
tests/test_conditions.py
tests/test_ftl_events.py
tests/test_rules.py