Metadata-Version: 1.2
Name: ftl-events
Version: 0.1.6
Summary: Experiments in event handling
Home-page: https://github.com/benthomasson/ftl_events
Author: Ben Thomasson
Author-email: ben.thomasson@gmail.com
License: Apache Software License 2.0
Keywords: ftl_events
Platform: UNKNOWN
Classifier: Development Status :: 2 - Pre-Alpha
Classifier: Intended Audience :: Developers
Classifier: License :: OSI Approved :: Apache Software License
Classifier: Natural Language :: English
Classifier: Programming Language :: Python :: 3
Classifier: Programming Language :: Python :: 3.6
Classifier: Programming Language :: Python :: 3.7
Classifier: Programming Language :: Python :: 3.8
Requires-Python: >=3.6
